pynamix/__init__.py
pynamix/data.py
pynamix/io.py
pynamix/measure.py
pynamix/testing.py
pynamix-0.0.2.dist-info/LICENSE.txt
pynamix-0.0.2.dist-info/METADATA
pynamix-0.0.2.dist-info/WHEEL
pynamix-0.0.2.dist-info/top_level.txt
pynamix-0.0.2.dist-info/RECORD
