Metadata-Version: 2.1
Name: pynamix
Version: 0.0.2
Summary: Tools for dealing with radiographs produced in DynamiX
Home-page: http://github.sydney.edu.au/scigem/pynamix
Author: Benjy Marks
Author-email: benjy.marks@sydney.edu.au
License: UNKNOWN
Platform: UNKNOWN
Classifier: Programming Language :: Python :: 3
Classifier: License :: OSI Approved :: GNU Lesser General Public License v3 or later (LGPLv3+)
Classifier: Operating System :: OS Independent
Classifier: Development Status :: 3 - Alpha
Requires-Python: >=3.6
